ccdt/__init__.py
ccdt/dataset/__init__.py
ccdt/dataset/main.py
ccdt/dataset/base_coco/__init__.py
ccdt/dataset/base_coco/base_coco.py
ccdt/dataset/base_csv/__init__.py
ccdt/dataset/base_csv/base_csv.py
ccdt/dataset/base_labelme/__init__.py
ccdt/dataset/base_labelme/async_io_task.py
ccdt/dataset/base_labelme/base_labelme.py
ccdt/dataset/base_voc/__init__.py
ccdt/dataset/base_voc/base_sys.py
ccdt/dataset/base_voc/base_txt.py
ccdt/dataset/base_voc/base_voc.py
ccdt/dataset/base_voc/base_xml.py
ccdt/dataset/base_voc/base_yolo.py
ccdt/dataset/base_voc/coco_to_labelme.py
ccdt/dataset/base_yolo/__init__.py
ccdt/dataset/utils/__init__.py
ccdt/dataset/utils/encoder.py
ccdt/dataset/utils/labelme_load.py
ccdt/fonts/simhei.ttf
ccdt/video_tool/__init__.py
ccdt/video_tool/split.py
ccdt/video_tool/video_main.py
ccdt-2.1.170.dist-info/LICENSE
ccdt-2.1.170.dist-info/METADATA
ccdt-2.1.170.dist-info/WHEEL
ccdt-2.1.170.dist-info/entry_points.txt
ccdt-2.1.170.dist-info/top_level.txt
ccdt-2.1.170.dist-info/RECORD
