Metadata-Version: 2.1
Name: ccdt
Version: 2.1.170
Summary: AI数据转换工具箱
Home-page: https://github.com/chipeak/chipeak_cv_data_tool
Author: zhanyong
Author-email: zhan.yong@chipeak.com
Project-URL: Bug Tracker, https://github.com/chipeak/chipeak_cv_data_tool/issues
Classifier: Programming Language :: Python :: 3.7
Classifier: License :: OSI Approved :: GNU Affero General Public License v3
Classifier: Operating System :: OS Independent
License-File: LICENSE
Requires-Dist: tqdm
Requires-Dist: opencv-python
Requires-Dist: numpy
Requires-Dist: pycocotools
Requires-Dist: prettytable
Requires-Dist: shapely
Requires-Dist: psutil
Requires-Dist: pypinyin
Requires-Dist: Pillow
Requires-Dist: aiofiles
Requires-Dist: moviepy
Requires-Dist: scikit-learn
Requires-Dist: pandas
Requires-Dist: openpyxl
Requires-Dist: xlrd
Requires-Dist: resource
